[
  [
    "01hs99np0h7skc7q5my27ardn8",
    { "expired": "2020-07-01", "from": "2013-01-01" }
  ],
  [
    "01hs99np0hmm24q0c2h060sj4m",
    { "from": "2018-08-01", "expired": "2020-11-06" }
  ],
  [
    "01hs99np0hs0zgcktvmh8sd99g",
    { "from": "2016-10-01", "expired": "2019-04-04" }
  ],
  [
    "01hs99np0j58rdz1a47wbb7a0g",
    { "from": "2022-04-01", "expired": "2022-04-30" }
  ],
  [
    "01hs99np0j7knysqrbmpj8thcs",
    { "from": "2015-05-01", "expired": "2018-04-30" }
  ],
  [
    "01hs99np0j8rp6pyncw90r6cvg",
    { "from": "2014-01-01", "expired": "2020-08-31" }
  ],
  [
    "01hs99np0jatc3d65jnq4k5jgd",
    { "from": "2018-04-15", "expired": "2022-05-31" }
  ],
  [
    "01hs99np0jd5039vbmkkbrpg86",
    { "from": "2013-01-15", "expired": "2018-12-31" }
  ],
  [
    "01hs99np0jeyftz3cwvzss13hh",
    { "from": "2022-10-01", "expired": "2023-03-31" }
  ],
  [
    "01hs99np0jfgs69krzq16hymc4",
    { "from": "2015-11-01", "expired": "2022-07-31" }
  ],
  [
    "01hs99np0jtcmwsrsytck4p8cw",
    { "from": "2011-08-01", "expired": "2021-01-31" }
  ],
  [
    "01hs99np0jv055ec6vh4t3s9zr",
    { "from": "2014-07-01", "expired": "2021-12-31" }
  ],
  [
    "01hs99np0jx06g5cqrvt8ab8dm",
    { "from": "2010-02-01", "expired": "2021-07-31" }
  ],
  [
    "01hs99np0jybdf6xda3qwh4s61",
    { "from": "2017-01-01", "expired": "2019-10-31" }
  ],
  [
    "01hs99np0jz79f6e1677wx8ntv",
    { "from": "2012-08-01", "expired": "2019-01-31" }
  ],
  [
    "01j7k9qzwpt7ffzpajk84mbr37",
    { "from": "1999-03-01", "expired": "2019-10-31" }
  ],
  ["aar", { "from": "2017-09-28" }],
  ["ach", { "from": "2019-06-03" }],
  ["aei", { "from": "2022-12-01" }],
  ["aen", { "from": "2016-05-02" }],
  ["aev", { "from": "1990-01-01" }],
  ["agi", { "from": "2000-01-31" }],
  ["ahz", { "from": "2015-08-31" }],
  ["aki", { "from": "2001-12-10" }],
  ["amn", { "from": "2014-07-01" }],
  ["anb", { "from": "2001-06-01" }],
  ["ara", { "from": "2022-01-01" }],
  ["asa", { "from": "2022-04-01", "expired": "2022-09-04" }],
  ["asi", { "from": "2023-05-01" }],
  ["ata", { "from": "2014-10-06" }],
  ["atf", { "from": "2003-03-01" }],
  ["avn", { "from": "2020-11-23" }],
  ["avs", { "from": "1997-07-22" }],
  ["azi", { "from": "2023-11-01" }],
  ["beb", { "from": "2019-08-01" }],
  ["bhw", { "from": "2019-08-01" }],
  ["bme", { "from": "2020-03-16", "expired": "2024-01-14" }],
  ["cab", { "from": "2014-08-28" }],
  ["che", { "from": "2020-09-01" }],
  ["chp", { "from": "2019-08-12" }],
  ["clh", { "from": "2011-06-01" }],
  ["cse", { "from": "2004-12-01" }],
  ["cst", { "from": "2008-11-01" }],
  ["ctw", { "from": "2020-10-19" }],
  ["eab", { "from": "2024-03-18" }],
  ["efl", { "from": "2023-10-01" }],
  ["ehh", { "from": "2023-03-01" }],
  ["ejw", { "from": "2018-07-06", "expired": "2021-07-30" }],
  ["ekr", { "from": "2023-08-01" }],
  ["elb", { "from": "2020-06-01", "expired": "2023-02-28" }],
  ["elo", { "from": "2004-07-01" }],
  ["ene", { "from": "2023-10-23", "expired": "2024-09-01" }],
  ["esy", { "from": "2021-06-07" }],
  [
    "esz",
    {
      "from": "2018-07-01",
      "expired": "2024-09-01"
    }
  ],
  ["eva", { "from": "2014-01-01" }],
  ["fac", { "from": "2023-01-01" }],
  ["fga", { "from": "2011-01-03", "expired": "2022-03-31" }],
  ["fma", { "from": "2022-08-01" }],
  ["frb", { "from": "2009-04-01", "expired": "2022-04-30" }],
  ["fst", { "from": "2023-10-01" }],
  ["gdh", { "from": "1994-07-01" }],
  ["ghr", { "from": "2004-05-01" }],
  ["gms", { "from": "2008-11-01" }],
  ["gnc", { "from": "1994-07-10" }],
  ["gwl", { "from": "2018-02-01", "expired": "2024-04-28" }],
  ["hab", { "from": "2024-05-06" }],
  ["hem", { "from": "2014-01-13" }],
  ["hes", { "from": "2018-06-25" }],
  ["hjb", { "from": "2022-01-17" }],
  ["hpm", { "from": "1989-03-26" }],
  ["hwh", { "from": "2024-06-03", "expired": "2024-08-23" }],
  ["ibo", { "from": "2017-07-03" }],
  ["icd", { "from": "2023-09-01" }],
  ["idh", { "from": "2005-04-01" }],
  ["ihw", { "from": "2015-01-01", "expired": "2024-04-10" }],
  ["imb", { "from": "2014-05-01" }],
  ["iyu", { "from": "2023-03-01" }],
  ["jee", { "from": "2024-10-03" }],
  ["jen", { "from": "2014-10-01" }],
  ["jha", { "from": "2010-11-01" }],
  ["jhi", { "from": "2021-10-01" }],
  ["jhp", { "from": "2007-06-01" }],
  ["jlc", { "from": "1997-09-01", "expired": "2022-06-30" }],
  ["jsj", { "from": "2022-03-01" }],
  ["jwk", { "from": "1985-11-15" }],
  ["kaj", { "from": "2021-03-01" }],
  ["kba", { "from": "2022-12-01" }],
  ["kbo", { "from": "2015-05-11" }],
  ["kdr", { "from": "2023-06-05" }],
  ["kdu", { "from": "2023-02-01" }],
  ["kej", { "from": "2022-09-01" }],
  ["kgp", { "from": "2024-09-26" }],
  ["khs", { "from": "2011-11-07" }],
  ["kis", { "from": "1999-10-19" }],
  [
    "kkr",
    {
      "from": "2024-01-01",
      "expired": "2024-10-31"
    }
  ],
  ["knj", { "from": "2024-06-17", "expired": "2024-08-19" }],
  ["kpb", { "from": "2011-10-01" }],
  ["krs", { "from": "2011-10-01" }],
  ["ksa", { "from": "2012-08-06" }],
  ["ksz", { "from": "2017-09-01" }],
  ["lca", { "from": "2004-09-01" }],
  ["lhl", { "from": "1990-05-30" }],
  ["lit", { "from": "2007-11-01" }],
  ["lka", { "from": "2014-07-01" }],
  ["lli", { "from": "2022-11-21" }],
  ["lne", { "from": "2022-10-03" }],
  ["los", { "from": "1995-12-01" }],
  ["lpi", { "from": "2024-02-26" }],
  ["lri", { "from": "2024-09-01" }],
  ["lsi", { "from": "2022-08-01" }],
  ["lut", { "from": "2014-03-24", "expired": "2022-12-31" }],
  ["maa", { "from": "2014-10-01", "expired": "2023-08-13" }],
  ["mad", { "from": "2016-08-01" }],
  ["mar", { "from": "2019-06-01" }],
  ["mbd", { "from": "2020-01-01", "expired": "2023-10-17" }],
  ["mfr", { "from": "2009-02-16" }],
  ["mib", { "from": "2022-08-22" }],
  ["mjh", { "from": "2023-08-15", "expired": "2024-10-31" }],
  ["mkr", { "from": "2020-03-01" }],
  ["mlc", { "from": "1997-06-03", "expired": "2022-06-30" }],
  ["mst", { "from": "1994-01-01" }],
  ["mth", { "from": "2020-06-01" }],
  ["mva", { "from": "2018-09-03" }],
  ["nmi", { "from": "2023-04-01" }],
  ["oan", { "from": "2012-01-01", "expired": "2022-03-31" }],
  ["obw", { "from": "2019-09-17" }],
  ["odj", { "from": "2012-10-01" }],
  ["oji", { "from": "1995-01-01" }],
  ["oyl", { "from": "2008-05-01" }],
  ["pae", { "from": "2013-05-01" }],
  ["pbl", { "from": "2019-05-01" }],
  ["per", { "from": "2005-09-01" }],
  ["pgh", { "from": "2014-01-15" }],
  ["pgl", { "from": "2023-05-01" }],
  ["pml", { "from": "2019-05-01" }],
  ["ppe", { "from": "2024-01-22", "expired": "2024-07-31" }],
  ["ppr", { "from": "2022-09-01" }],
  ["qin", { "from": "2014-09-19" }],
  ["rap", { "from": "2014-05-01" }],
  ["ref", { "from": "2005-01-01", "expired": "2023-12-31" }],
  ["rfr", { "from": "2018-09-03", "expired": "2023-09-29" }],
  ["rpa", { "from": "1992-06-01" }],
  ["rst", { "from": "2021-06-07" }],
  ["rve", { "from": "1993-08-01" }],
  ["sam", { "from": "2023-03-01" }],
  ["sda", { "from": "1988-01-01" }],
  ["sde", { "from": "2013-08-05" }],
  ["sdo", { "from": "2024-06-01", "expired": "2024-08-23" }],
  ["sfp", { "from": "2013-05-01", "expired": "2023-04-28" }],
  ["sgu", { "from": "2004-11-01" }],
  ["she", { "from": "2018-04-01" }],
  ["skc", { "from": "1992-06-06" }],
  ["skd", { "from": "2024-02-01" }],
  ["sll", { "from": "2024-08-19" }],
  ["spe", { "from": "2022-04-20" }],
  ["sta", { "from": "2015-02-01", "expired": "2022-05-31" }],
  ["svi", { "from": "2024-08-19" }],
  ["svl", { "from": "2021-05-01" }],
  ["tbo", { "from": "2014-12-01" }],
  ["thh", { "from": "2014-01-06", "expired": "2023-02-28" }],
  ["tko", { "from": "2020-12-01" }],
  ["tmj", { "from": "2013-09-09" }],
  ["tom", { "from": "2014-05-01" }],
  ["tri", { "from": "2011-11-14" }],
  ["tvg", { "from": "2017-08-28" }],
  ["vho", { "from": "2021-04-26" }],
  ["vra", { "from": "2020-02-03" }],
  ["vre", { "from": "2000-06-26", "expired": "2024-03-15" }],
  ["vsa", { "from": "1998-09-01" }],
  ["wkr", { "from": "2011-10-01" }],
  ["xwa", { "from": "2023-08-01" }],
  ["yns", { "from": "2018-01-01" }],
  ["ysh", { "from": "2021-08-16" }]
]
